Traceback (most recent call last):
  File "<string>", line 1, in <module>
    import marshal, dis, sys; f = open('wallhaven_gui.cpython-314.pyc', 'rb'); f.read(16); code = marshal.load(f); dis.dis(code)
                                                                                                                   ~~~~~~~^^^^^^
  File "C:\Users\13640\AppData\Local\Python\pythoncore-3.14-64\Lib\dis.py", line 123, in dis
    _disassemble_recursive(x, file=file, depth=depth, show_caches=show_caches, adaptive=adaptive, show_offsets=show_offsets, show_positions=show_positions)
    ~~~~~~~~~~~~~~~~~~~~~~^^^^^^^^^^^^^^^^^^^^^^^^^^^^^^^^^^^^^^^^^^^^^^^^^^^^^^^^^^^^^^^^^^^^^^^^^^^^^^^^^^^^^^^^^^^^^^^^^^^^^^^^^^^^^^^^^^^^^^^^^^^^^^^^^
  File "C:\Users\13640\AppData\Local\Python\pythoncore-3.14-64\Lib\dis.py", line 844, in _disassemble_recursive
    _disassemble_recursive(
    ~~~~~~~~~~~~~~~~~~~~~~^
        x, file=file, depth=depth, show_caches=show_caches,
        ^^^^^^^^^^^^^^^^^^^^^^^^^^^^^^^^^^^^^^^^^^^^^^^^^^^
        adaptive=adaptive, show_offsets=show_offsets, show_positions=show_positions
        ^^^^^^^^^^^^^^^^^^^^^^^^^^^^^^^^^^^^^^^^^^^^^^^^^^^^^^^^^^^^^^^^^^^^^^^^^^^
    )
    ^
  File "C:\Users\13640\AppData\Local\Python\pythoncore-3.14-64\Lib\dis.py", line 844, in _disassemble_recursive
    _disassemble_recursive(
    ~~~~~~~~~~~~~~~~~~~~~~^
        x, file=file, depth=depth, show_caches=show_caches,
        ^^^^^^^^^^^^^^^^^^^^^^^^^^^^^^^^^^^^^^^^^^^^^^^^^^^
        adaptive=adaptive, show_offsets=show_offsets, show_positions=show_positions
        ^^^^^^^^^^^^^^^^^^^^^^^^^^^^^^^^^^^^^^^^^^^^^^^^^^^^^^^^^^^^^^^^^^^^^^^^^^^
    )
    ^
  File "C:\Users\13640\AppData\Local\Python\pythoncore-3.14-64\Lib\dis.py", line 836, in _disassemble_recursive
    disassemble(co, file=file, show_caches=show_caches, adaptive=adaptive, show_offsets=show_offsets, show_positions=show_positions)
    ~~~~~~~~~~~^^^^^^^^^^^^^^^^^^^^^^^^^^^^^^^^^^^^^^^^^^^^^^^^^^^^^^^^^^^^^^^^^^^^^^^^^^^^^^^^^^^^^^^^^^^^^^^^^^^^^^^^^^^^^^^^^^^^^
  File "C:\Users\13640\AppData\Local\Python\pythoncore-3.14-64\Lib\dis.py", line 831, in disassemble
    _disassemble_bytes(_get_code_array(co, adaptive), lasti, linestarts,
    ~~~~~~~~~~~~~~~~~~^^^^^^^^^^^^^^^^^^^^^^^^^^^^^^^^^^^^^^^^^^^^^^^^^^
                       exception_entries=exception_entries, co_positions=co.co_positions(),
                       ^^^^^^^^^^^^^^^^^^^^^^^^^^^^^^^^^^^^^^^^^^^^^^^^^^^^^^^^^^^^^^^^^^^^
                       original_code=co.co_code, arg_resolver=arg_resolver, formatter=formatter)
                       ^^^^^^^^^^^^^^^^^^^^^^^^^^^^^^^^^^^^^^^^^^^^^^^^^^^^^^^^^^^^^^^^^^^^^^^^^
  File "C:\Users\13640\AppData\Local\Python\pythoncore-3.14-64\Lib\dis.py", line 910, in _disassemble_bytes
    print_instructions(instrs, exception_entries, formatter, lasti=lasti)
    ~~~~~~~~~~~~~~~~~~^^^^^^^^^^^^^^^^^^^^^^^^^^^^^^^^^^^^^^^^^^^^^^^^^^^
  File "C:\Users\13640\AppData\Local\Python\pythoncore-3.14-64\Lib\dis.py", line 918, in print_instructions
    formatter.print_instruction(instr, is_current_instr)
    ~~~~~~~~~~~~~~~~~~~~~~~~~~~^^^^^^^^^^^^^^^^^^^^^^^^^
  File "C:\Users\13640\AppData\Local\Python\pythoncore-3.14-64\Lib\dis.py", line 464, in print_instruction
    self.print_instruction_line(instr, mark_as_current)
    ~~~~~~~~~~~~~~~~~~~~~~~~~~~^^^^^^^^^^^^^^^^^^^^^^^^
  File "C:\Users\13640\AppData\Local\Python\pythoncore-3.14-64\Lib\dis.py", line 542, in print_instruction_line
    print(' '.join(fields).rstrip(), file=self.file)
    ~~~~~^^^^^^^^^^^^^^^^^^^^^^^^^^^^^^^^^^^^^^^^^^^
UnicodeEncodeError: 'gbk' codec can't encode character '\u26a0' in position 47: illegal multibyte sequence
  0           RESUME                   0

  1           LOAD_CONST               0 ('\nWallhaven ±⁄÷Ωœ¬‘ÿ∆˜ - GUI ∞Ê±æ\n π”√ CustomTkinter ππΩ®œ÷¥˙ªØΩÁ√Ê\n÷ß≥÷∫ÛÃ®≈˙¡øœ¬‘ÿ + «∞Ã® ÷∂Ø‘§¿¿\n')
              STORE_NAME               0 (__doc__)

  6           LOAD_SMALL_INT           0
              LOAD_CONST               1 (None)
              IMPORT_NAME              1 (customtkinter)
              STORE_NAME               2 (ctk)

  7           LOAD_SMALL_INT           0
              LOAD_CONST               2 (('filedialog', 'messagebox'))
              IMPORT_NAME              3 (tkinter)
              IMPORT_FROM              4 (filedialog)
              STORE_NAME               4 (filedialog)
              IMPORT_FROM              5 (messagebox)
              STORE_NAME               5 (messagebox)
              POP_TOP

  8           LOAD_SMALL_INT           0
              LOAD_CONST               1 (None)
              IMPORT_NAME              6 (threading)
              STORE_NAME               6 (threading)

  9           LOAD_SMALL_INT           0
              LOAD_CONST               1 (None)
              IMPORT_NAME              7 (requests)
              STORE_NAME               7 (requests)

 10           LOAD_SMALL_INT           0
              LOAD_CONST               1 (None)
              IMPORT_NAME              8 (os)
              STORE_NAME               8 (os)

 11           LOAD_SMALL_INT           0
              LOAD_CONST               1 (None)
              IMPORT_NAME              9 (time)
              STORE_NAME               9 (time)

 12           LOAD_SMALL_INT           0
              LOAD_CONST               1 (None)
              IMPORT_NAME             10 (json)
              STORE_NAME              10 (json)

 13           LOAD_SMALL_INT           0
              LOAD_CONST               1 (None)
              IMPORT_NAME             11 (re)
              STORE_NAME              11 (re)

 14           LOAD_SMALL_INT           0
              LOAD_CONST               3 (('Path',))
              IMPORT_NAME             12 (pathlib)
              IMPORT_FROM             13 (Path)
              STORE_NAME              13 (Path)
              POP_TOP

 15           LOAD_SMALL_INT           0
              LOAD_CONST               4 (('GoogleTranslator',))
              IMPORT_NAME             14 (deep_translator)
              IMPORT_FROM             15 (GoogleTranslator)
              STORE_NAME              15 (GoogleTranslator)
              POP_TOP

 16           LOAD_SMALL_INT           0
              LOAD_CONST               5 (('Image', 'ImageTk'))
              IMPORT_NAME             16 (PIL)
              IMPORT_FROM             17 (Image)
              STORE_NAME              17 (Image)
              IMPORT_FROM             18 (ImageTk)
              STORE_NAME              18 (ImageTk)
              POP_TOP

 17           LOAD_SMALL_INT           0
              LOAD_CONST               1 (None)
              IMPORT_NAME             19 (io)
              STORE_NAME              19 (io)

 20           LOAD_BUILD_CLASS
              PUSH_NULL
              LOAD_CONST               6 (<code object ConfigManager at 0x000001DB021A3660, file "wallhaven_gui.py", line 20>)
              MAKE_FUNCTION
              LOAD_CONST               7 ('ConfigManager')
              CALL                     2
              STORE_NAME              20 (ConfigManager)

 76           LOAD_BUILD_CLASS
              PUSH_NULL
              LOAD_CONST               8 (<code object WallhavenDownloader at 0x000001DB023A3C70, file "wallhaven_gui.py", line 76>)
              MAKE_FUNCTION
              LOAD_CONST               9 ('WallhavenDownloader')
              CALL                     2
              STORE_NAME              21 (WallhavenDownloader)

417           LOAD_BUILD_CLASS
              PUSH_NULL
              LOAD_CONST              10 (<code object WallhavenGUI at 0x000001DB02017630, file "wallhaven_gui.py", line 417>)
              MAKE_FUNCTION
              LOAD_CONST              11 ('WallhavenGUI')
              CALL                     2
              STORE_NAME              22 (WallhavenGUI)

974           LOAD_NAME               23 (__name__)
              LOAD_CONST              12 ('__main__')
              COMPARE_OP              88 (bool(==))
              POP_JUMP_IF_FALSE       26 (to L1)
              NOT_TAKEN

975           LOAD_NAME               22 (WallhavenGUI)
              PUSH_NULL
              CALL                     0
              STORE_NAME              24 (app)

976           LOAD_NAME               24 (app)
              LOAD_ATTR               51 (run + NULL|self)
              CALL                     0
              POP_TOP
              LOAD_CONST               1 (None)
              RETURN_VALUE

974   L1:     LOAD_CONST               1 (None)
              RETURN_VALUE

Disassembly of <code object ConfigManager at 0x000001DB021A3660, file "wallhaven_gui.py", line 20>:
  --           MAKE_CELL                0 (__classdict__)

  20           RESUME                   0
               LOAD_NAME                0 (__name__)
               STORE_NAME               1 (__module__)
               LOAD_CONST               0 ('ConfigManager')
               STORE_NAME               2 (__qualname__)
               LOAD_SMALL_INT          20
               STORE_NAME               3 (__firstlineno__)
               LOAD_LOCALS
               STORE_DEREF              0 (__classdict__)

  21           LOAD_CONST               1 ('≈‰÷√πÐ¿Ì¿ý - ∏∫‘±£¥Ê∫Õº”‘ÿ”√ªß…Ë÷√')
               STORE_NAME               4 (__doc__)

  23           LOAD_CONST               7 (('wallhaven_config.json',))
               LOAD_CONST               2 (<code object __init__ at 0x000001DB020162B0, file "wallhaven_gui.py", line 23>)
               MAKE_FUNCTION
               SET_FUNCTION_ATTRIBUTE   1 (defaults)
               STORE_NAME               5 (__init__)

  38           LOAD_CONST               3 (<code object load_config at 0x000001DB02301500, file "wallhaven_gui.py", line 38>)
               MAKE_FUNCTION
               STORE_NAME               6 (load_config)

  52           LOAD_CONST               4 (<code object save_config at 0x000001DB02554A30, file "wallhaven_gui.py", line 52>)
               MAKE_FUNCTION
               STORE_NAME               7 (save_config)
               LOAD_CONST               5 (('config_file', 'default_config'))
               STORE_NAME               8 (__static_attributes__)
               LOAD_FAST_BORROW         0 (__classdict__)
               STORE_NAME               9 (__classdictcell__)
               LOAD_CONST               6 (None)
               RETURN_VALUE

Disassembly of <code object __init__ at 0x000001DB020162B0, file "wallhaven_gui.py", line 23>:
 23           RESUME                   0

 24           LOAD_FAST_BORROW_LOAD_FAST_BORROW 16 (config_file, self)
              STORE_ATTR               0 (config_file)

 26           LOAD_CONST               0 ('keyword')
              LOAD_CONST               1 ('anime')

 27           LOAD_CONST               2 ('count')
              LOAD_CONST               3 ('100')

 28           LOAD_CONST               4 ('save_path')
              LOAD_GLOBAL              2 (os)
              LOAD_ATTR                4 (path)
              LOAD_ATTR                7 (join + NULL|self)
              LOAD_GLOBAL              2 (os)
              LOAD_ATTR                8 (getcwd)
              PUSH_NULL
              CALL                     0
              LOAD_CONST               5 ('anime_wallpapers')
              CALL                     2

 29           LOAD_CONST               6 ('category_general')
              LOAD_CONST               7 (True)

 30           LOAD_CONST               8 ('category_anime')
              LOAD_CONST               7 (True)

 31           LOAD_CONST               9 ('category_people')
              LOAD_CONST              10 (False)

 32           LOAD_CONST              11 ('purity_sfw')
              LOAD_CONST               7 (True)

 33           LOAD_CONST              12 ('purity_sketchy')
              LOAD_CONST               7 (True)

 34           LOAD_CONST              13 ('purity_nsfw')
              LOAD_CONST              10 (False)

 35           LOAD_CONST              14 ('api_key')
              LOAD_CONST              15 ('')

 25           BUILD_MAP               10
              LOAD_FAST_BORROW         0 (self)
              STORE_ATTR               5 (default_config)
              LOAD_CONST              16 (None)
              RETURN_VALUE

Disassembly of <code object load_config at 0x000001DB02301500, file "wallhaven_gui.py", line 38>:
  38            RESUME                   0

  40            NOP

  41    L1:     LOAD_GLOBAL              0 (os)
                LOAD_ATTR                2 (path)
                LOAD_ATTR                5 (exists + NULL|self)
                LOAD_FAST_BORROW         0 (self)
                LOAD_ATTR                6 (config_file)
                CALL                     1
                TO_BOOL
                POP_JUMP_IF_FALSE       82 (to L7)
        L2:     NOT_TAKEN

  42    L3:     LOAD_GLOBAL              9 (open + NULL)
                LOAD_FAST_BORROW         0 (self)
                LOAD_ATTR                6 (config_file)
                LOAD_CONST               1 ('r')
                LOAD_CONST               2 ('utf-8')
                LOAD_CONST               3 (('encoding',))
                CALL_KW                  3
                COPY                     1
                LOAD_SPECIAL             1 (__exit__)
                SWAP                     2
                SWAP                     3
                LOAD_SPECIAL             0 (__enter__)
                CALL                     0
        L4:     STORE_FAST               1 (f)

  43            LOAD_GLOBAL             10 (json)
                LOAD_ATTR               12 (load)
                PUSH_NULL
                LOAD_FAST_BORROW         1 (f)
                CALL                     1
                STORE_FAST               2 (config)

  45            BUILD_MAP                0
                LOAD_FAST_BORROW         0 (self)
                LOAD_ATTR               14 (default_config)
                DICT_UPDATE              1
                LOAD_FAST_BORROW         2 (config)
                DICT_UPDATE              1

  42    L5:     SWAP                     3
                SWAP                     2
                LOAD_CONST               4 (None)
                LOAD_CONST               4 (None)
                LOAD_CONST               4 (None)
                CALL                     3
                POP_TOP
        L6:     RETURN_VALUE

  47    L7:     LOAD_FAST_BORROW         0 (self)
                LOAD_ATTR               14 (default_config)
                LOAD_ATTR               17 (copy + NULL|self)
                CALL                     0
        L8:     RETURN_VALUE

  42    L9:     PUSH_EXC_INFO
                WITH_EXCEPT_START
                TO_BOOL
                POP_JUMP_IF_TRUE         2 (to L10)
                NOT_TAKEN
                RERAISE                  2
       L10:     POP_TOP
       L11:     POP_EXCEPT
                POP_TOP
                POP_TOP
                POP_TOP
       L12:     LOAD_CONST               4 (None)
                RETURN_VALUE

  --   L13:     COPY                     3
                POP_EXCEPT
                RERAISE                  1
       L14:     PUSH_EXC_INFO

  48            LOAD_GLOBAL             18 (Exception)
                CHECK_EXC_MATCH
                POP_JUMP_IF_FALSE       52 (to L19)
                NOT_TAKEN
                STORE_FAST               3 (e)

  49   L15:     LOAD_GLOBAL             21 (print + NULL)
                LOAD_CONST               5 ('º”‘ÿ≈‰÷√ ß∞Ð£∫')
                LOAD_FAST                3 (e)
                FORMAT_SIMPLE
                LOAD_CONST               6 ('£¨ π”√ƒ¨»œ≈‰÷√')
                BUILD_STRING             3
                CALL                     1
                POP_TOP

  50            LOAD_FAST                0 (self)
                LOAD_ATTR               14 (default_config)
                LOAD_ATTR               17 (copy + NULL|self)
                CALL                     0
       L16:     SWAP                     2
       L17:     POP_EXCEPT
                LOAD_CONST               4 (None)
                STORE_FAST               3 (e)
                DELETE_FAST              3 (e)
                RETURN_VALUE

  --   L18:     LOAD_CONST               4 (None)
                STORE_FAST               3 (e)
                DELETE_FAST              3 (e)
                RERAISE                  1

  48   L19:     RERAISE                  0

  --   L20:     COPY                     3
                POP_EXCEPT
                RERAISE                  1
ExceptionTable:
  L1 to L2 -> L14 [0]
  L3 to L4 -> L14 [0]
  L4 to L5 -> L9 [2] lasti
  L5 to L6 -> L14 [0]
  L7 to L8 -> L14 [0]
  L9 to L11 -> L13 [4] lasti
  L11 to L12 -> L14 [0]
  L13 to L14 -> L14 [0]
  L14 to L15 -> L20 [1] lasti
  L15 to L16 -> L18 [1] lasti
  L16 to L17 -> L20 [1] lasti
  L18 to L20 -> L20 [1] lasti

Disassembly of <code object save_config at 0x000001DB02554A30, file "wallhaven_gui.py", line 52>:
  52            RESUME                   0

  55            NOP

  57    L1:     LOAD_CONST               1 ('keyword')
                LOAD_FAST_BORROW         1 (keyword)

  58            LOAD_CONST               2 ('count')
                LOAD_FAST_BORROW         2 (count)

  59            LOAD_CONST               3 ('save_path')
                LOAD_FAST_BORROW         3 (save_path)

  60            LOAD_CONST               4 ('category_general')
                LOAD_FAST_BORROW         4 (category_general)

  61            LOAD_CONST               5 ('category_anime')
                LOAD_FAST_BORROW         5 (category_anime)

  62            LOAD_CONST               6 ('category_people')
                LOAD_FAST_BORROW         6 (category_people)

  63            LOAD_CONST               7 ('purity_sfw')
                LOAD_FAST_BORROW         7 (purity_sfw)

  64            LOAD_CONST               8 ('purity_sketchy')
                LOAD_FAST_BORROW         8 (purity_sketchy)

  65            LOAD_CONST               9 ('purity_nsfw')
                LOAD_FAST_BORROW         9 (purity_nsfw)

  66            LOAD_CONST              10 ('api_key')
                LOAD_FAST_BORROW        10 (api_key)

  56            BUILD_MAP               10
                STORE_FAST              11 (config)

  68            LOAD_GLOBAL              1 (open + NULL)
                LOAD_FAST_BORROW         0 (self)
                LOAD_ATTR                2 (config_file)
                LOAD_CONST              11 ('w')
                LOAD_CONST              12 ('utf-8')
                LOAD_CONST              13 (('encoding',))
                CALL_KW                  3
                COPY                     1
                LOAD_SPECIAL             1 (__exit__)
                SWAP                     2
                SWAP                     3
                LOAD_SPECIAL             0 (__enter__)
                CALL                     0
        L2:     STORE_FAST              12 (f)

  69            LOAD_GLOBAL              4 (json)
                LOAD_ATTR                6 (dump)
                PUSH_NULL
                LOAD_FAST_BORROW_LOAD_FAST_BORROW 188 (config, f)
                LOAD_CONST              14 (False)
                LOAD_SMALL_INT           4
                LOAD_CONST              15 (('ensure_ascii', 'indent'))
                CALL_KW                  4
                POP_TOP

  68    L3:     LOAD_CONST              16 (None)
                LOAD_CONST              16 (None)
                LOAD_CONST              16 (None)
                CALL                     3
                POP_TOP

  70    L4:     LOAD_CONST              17 (True)
                RETURN_VALUE

  68    L5:     PUSH_EXC_INFO
                WITH_EXCEPT_START
                TO_BOOL
                POP_JUMP_IF_TRUE         2 (to L6)
                NOT_TAKEN
                RERAISE                  2
        L6:     POP_TOP
        L7:     POP_EXCEPT
                POP_TOP
                POP_TOP
                POP_TOP

  70    L8:     LOAD_CONST              17 (True)
                RETURN_VALUE

  --    L9:     COPY                     3
                POP_EXCEPT
                RERAISE                  1
       L10:     PUSH_EXC_INFO

  71            LOAD_GLOBAL              8 (Exception)
                CHECK_EXC_MATCH
                POP_JUMP_IF_FALSE       26 (to L14)
                NOT_TAKEN
                STORE_FAST              13 (e)

  72   L11:     LOAD_GLOBAL             11 (print + NULL)
                LOAD_CONST              18 ('±£¥Ê≈‰÷√ ß∞Ð£∫')
                LOAD_FAST               13 (e)
                FORMAT_SIMPLE
                BUILD_STRING             2
                CALL                     1
                POP_TOP

  73   L12:     POP_EXCEPT
                LOAD_CONST              16 (None)
                STORE_FAST              13 (e)
                DELETE_FAST             13 (e)
                LOAD_CONST              14 (False)
                RETURN_VALUE

  --   L13:     LOAD_CONST              16 (None)
                STORE_FAST              13 (e)
                DELETE_FAST             13 (e)
                RERAISE                  1

  71   L14:     RERAISE                  0

  --   L15:     COPY                     3
                POP_EXCEPT
                RERAISE                  1
ExceptionTable:
  L1 to L2 -> L10 [0]
  L2 to L3 -> L5 [2] lasti
  L3 to L4 -> L10 [0]
  L5 to L7 -> L9 [4] lasti
  L7 to L8 -> L10 [0]
  L9 to L10 -> L10 [0]
  L10 to L11 -> L15 [1] lasti
  L11 to L12 -> L13 [1] lasti
  L13 to L15 -> L15 [1] lasti

Disassembly of <code object WallhavenDownloader at 0x000001DB023A3C70, file "wallhaven_gui.py", line 76>:
  --           MAKE_CELL                0 (__classdict__)

  76           RESUME                   0
               LOAD_NAME                0 (__name__)
               STORE_NAME               1 (__module__)
               LOAD_CONST               0 ('WallhavenDownloader')
               STORE_NAME               2 (__qualname__)
               LOAD_SMALL_INT          76
               STORE_NAME               3 (__firstlineno__)
               LOAD_LOCALS
               STORE_DEREF              0 (__classdict__)

  77           LOAD_CONST               1 ('±⁄÷Ωœ¬‘ÿ∫À–ƒ¬þº≠¿ý')
               STORE_NAME               4 (__doc__)

  80           BUILD_MAP                0

  82           LOAD_CONST               2 ('∫˙Ã“')
               LOAD_CONST               3 ('hu tao')

  80           MAP_ADD                  1

  83           LOAD_CONST               4 ('∏ ”Í')
               LOAD_CONST               5 ('ganyu')

  80           MAP_ADD                  1

  84           LOAD_CONST               6 ('¿◊µÁΩ´æ¸')
               LOAD_CONST               7 ('raiden shogun')

  80           MAP_ADD                  1

  85           LOAD_CONST               8 ('∞À÷ÿ…Ò◊”')
               LOAD_CONST               9 ('yae miko')

  80           MAP_ADD                  1

  86           LOAD_CONST              10 ('…Ò¿ÔÁ±ª™')
               LOAD_CONST              11 ('ayaka')

  80           MAP_ADD                  1

  87           LOAD_CONST              12 ('œ¸π¨')
               LOAD_CONST              13 ('yoimiya')

  80           MAP_ADD                  1

  88           LOAD_CONST              14 ('∑„‘≠ÕÚ“∂')
               LOAD_CONST              15 ('kazuha')

  80           MAP_ADD                  1

  89           LOAD_CONST              16 ('…∫∫˜π¨–ƒ∫£')
               LOAD_CONST              17 ('kokomi')

  80           MAP_ADD                  1

  90           LOAD_CONST              18 ('Õ–¬Ì')
               LOAD_CONST              19 ('thoma')

  80           MAP_ADD                  1

  91           LOAD_CONST              20 ('ªƒû{“ª∂∑')
               LOAD_CONST              21 ('itto')

  80           MAP_ADD                  1

  92           LOAD_CONST              22 ('‘∆ð¿')
               LOAD_CONST              23 ('yun jin')

  80           MAP_ADD                  1

  93           LOAD_CONST              24 ('…Í∫◊')
               LOAD_CONST              25 ('shenhe')

  80           MAP_ADD                  1

  94           LOAD_CONST              26 ('“π¿º')
               LOAD_CONST              27 ('yelan')

  80           MAP_ADD                  1

  95           LOAD_CONST              28 ('æ√·™»Ã')
               LOAD_CONST              29 ('kuki shinobu')

  80           MAP_ADD                  1

  96           LOAD_CONST              30 ('¬π“∞‘∫∆Ω≤ÿ')
               LOAD_CONST              31 ('heizou')

  80           MAP_ADD                  1

  97           LOAD_CONST              32 ('Ã·ƒ…¿Ô')
               LOAD_CONST              33 ('tighnari')

  80           MAP_ADD                  1

  98           LOAD_CONST              34 ('ø¬¿≥')
               LOAD_CONST              35 ('collei')

  80           MAP_ADD                  1
               BUILD_MAP                0

  99           LOAD_CONST              36 ('∂ý¿Ú')
               LOAD_CONST              37 ('dori')

  80           MAP_ADD                  1

 100           LOAD_CONST              38 ('»¸≈µ')
               LOAD_CONST              39 ('cyno')

  80           MAP_ADD                  1

 101           LOAD_CONST              40 ('ƒð¬∂')
               LOAD_CONST              41 ('nilou')

  80           MAP_ADD                  1

 102           LOAD_CONST              42 ('ƒ…Œ˜Êß')
               LOAD_CONST              43 ('nahida')

  80           MAP_ADD                  1

 103           LOAD_CONST              44 ('¿≥“¿¿≠')
               LOAD_CONST              45 ('layla')

  80           MAP_ADD                  1

 104           LOAD_CONST              46 ('¡˜¿À’þ')
               LOAD_CONST              47 ('wanderer')

  80           MAP_ADD                  1

 105           LOAD_CONST              48 ('∑©¬∂…∫')
               LOAD_CONST              49 ('faruzan')

  80           MAP_ADD                  1

 106           LOAD_CONST              50 ('∞¨∂˚∫£…≠')
               LOAD_CONST              51 ('alhaitham')

  80           MAP_ADD                  1

 107           LOAD_CONST              52 ('—˛—˛')
               LOAD_CONST              53 ('yaoyao')

  80           MAP_ADD                  1

 108           LOAD_CONST              54 ('µœœ£—≈')
               LOAD_CONST              55 ('dehya')

  80           MAP_ADD                  1

 109           LOAD_CONST              56 ('√◊ø®')
               LOAD_CONST              57 ('mika')

  80           MAP_ADD                  1

 110           LOAD_CONST              58 ('ø®Œ¨')
               LOAD_CONST              59 ('kaveh')

  80           MAP_ADD                  1

 111           LOAD_CONST              60 ('∞◊ ı')
               LOAD_CONST              61 ('baizhu')

  80           MAP_ADD                  1

 112           LOAD_CONST              62 ('¡’ƒðÃÿ')
               LOAD_CONST              63 ('lynette')

  80           MAP_ADD                  1

 113           LOAD_CONST              64 ('¡÷ƒ·')
               LOAD_CONST              65 ('lyney')

  80           MAP_ADD                  1

 114           LOAD_CONST              66 ('∑∆√◊ƒ·')
               LOAD_CONST              67 ('freminet')

  80           MAP_ADD                  1

 115           LOAD_CONST              68 ('ƒ«Œ¨¿≥Ãÿ')
               LOAD_CONST              69 ('neuvillette')

  80           MAP_ADD                  1
               DICT_UPDATE              1
               BUILD_MAP                0

 116           LOAD_CONST              70 ('¿≥≈∑Àπ¿˚')
               LOAD_CONST              71 ('wriothesley')

  80           MAP_ADD                  1

 117           LOAD_CONST              72 ('œƒ¬ÂµŸ')
               LOAD_CONST              73 ('charlotte')

  80           MAP_ADD                  1

 118           LOAD_CONST              74 ('ÐΩƒ˛ƒ»')
               LOAD_CONST              75 ('furina')

  80           MAP_ADD                  1

 119           LOAD_CONST              76 ('ƒ»Œ¨Ê´')
               LOAD_CONST              77 ('navia')

  80           MAP_ADD                  1

 120           LOAD_CONST              78 ('œƒŒ÷¿Ÿ')
               LOAD_CONST              79 ('chevreuse')

  80           MAP_ADD                  1

 121           LOAD_CONST              80 ('œ–‘∆')
               LOAD_CONST              81 ('xianyun')

  80           MAP_ADD                  1

 122           LOAD_CONST              82 ('ºŒ√˜')
               LOAD_CONST              83 ('gaming')

  80           MAP_ADD                  1

 123           LOAD_CONST              84 ('«ß÷Ø')
               LOAD_CONST              85 ('chiori')

  80           MAP_ADD                  1

 124           LOAD_CONST              86 ('∞¢¿Ÿ∆Ê≈µ')
               LOAD_CONST              87 ('arlecchino')

  80           MAP_ADD                  1

 125           LOAD_CONST              88 ('»˚À˛¿Ÿ')
               LOAD_CONST              89 ('sethos')

  80           MAP_ADD                  1

 126           LOAD_CONST              90 ('øÀ¬Â¡’µ¬')
               LOAD_CONST              91 ('clorinde')

  80           MAP_ADD                  1

 127           LOAD_CONST              92 ('œ£∏Òˆ©')
               LOAD_CONST              93 ('sigewinne')

  80           MAP_ADD                  1

 128           LOAD_CONST              94 ('∞¨√∑¿Ú∞£')
               LOAD_CONST              95 ('emilie')

  80           MAP_ADD                  1

 129           LOAD_CONST              96 ('ø®∆Îƒ»')
               LOAD_CONST              97 ('kachina')

  80           MAP_ADD                  1

 130           LOAD_CONST              98 ('ª˘ƒ·∆Ê')
               LOAD_CONST              99 ('kinich')

  80           MAP_ADD                  1

 131           LOAD_CONST             100 ('¬Í¿≠ƒð')
               LOAD_CONST             101 ('mualani')

  80           MAP_ADD                  1

 132           LOAD_CONST             102 ('œ£≈µƒ˛')
               LOAD_CONST             103 ('xilonen')

  80           MAP_ADD                  1
               DICT_UPDATE              1

 133           LOAD_CONST             104 ('«°Àπø®')
               LOAD_CONST             105 ('chasca')

 134           LOAD_CONST             106 ('∞¬¬Ð¿≠')
               LOAD_CONST             107 ('ororon')

 135           LOAD_CONST             108 ('¬ÍÞ±ø®')
               LOAD_CONST             109 ('mavuika')

 136           LOAD_CONST             110 ('ÐÁÃÿ«â¿Ú')
               LOAD_CONST             111 ('citlali')

 137           LOAD_CONST             112 ('¿º')
               LOAD_CONST             113 ('lan')

 140           LOAD_CONST             114 ('≥ı“ÙŒ¥¿¥')
               LOAD_CONST             115 ('hatsune miku')

 141           LOAD_CONST             116 ('¿Ÿƒ∑')
               LOAD_CONST             117 ('rem')

 142           LOAD_CONST             118 ('¿≠ƒ∑')
               LOAD_CONST             119 ('ram')

 143           LOAD_CONST             120 ('02')
               LOAD_CONST             121 ('zero two')

 146           LOAD_CONST             122 ('‘≠…Ò')
               LOAD_CONST             123 ('genshin impact')

 147           LOAD_CONST             124 ('±¿ªµ')
               LOAD_CONST             125 ('honkai')

 148           LOAD_CONST             126 ('√˜»’∑Ω÷€')
               LOAD_CONST             127 ('arknights')

 149           LOAD_CONST             128 ('±Ã¿∂∫Ωœþ')
               LOAD_CONST             129 ('azur lane')

  80           BUILD_MAP               13
               DICT_UPDATE              1
               STORE_NAME               5 (PROPER_NOUNS)

 152           LOAD_CONST             141 (('anime', 'anime_wallpapers', 1000, None, True, True, False, True, True, False, '', None))
               LOAD_CONST             131 (<code object __init__ at 0x000001DB020223D0, file "wallhaven_gui.py", line 152>)
               MAKE_FUNCTION
               SET_FUNCTION_ATTRIBUTE   1 (defaults)
               STORE_NAME               6 (__init__)

 182           LOAD_CONST             132 (<code object _build_categories_string at 0x000001DB022149B0, file "wallhaven_gui.py", line 182>)
               MAKE_FUNCTION
               STORE_NAME               7 (_build_categories_string)

 190           LOAD_CONST             133 (<code object _build_purity_string at 0x000001DB02214160, file "wallhaven_gui.py", line 190>)
               MAKE_FUNCTION
               STORE_NAME               8 (_build_purity_string)

 198           LOAD_CONST             134 (<code object log at 0x000001DB021B6F70, file "wallhaven_gui.py", line 198>)
               MAKE_FUNCTION
               STORE_NAME               9 (log)

 203           LOAD_CONST             135 (<code object contains_chinese at 0x000001DB021B71B0, file "wallhaven_gui.py", line 203>)
               MAKE_FUNCTION
               STORE_NAME              10 (contains_chinese)

 207           LOAD_CONST             136 (<code object translate_to_english at 0x000001DB02554830, file "wallhaven_gui.py", line 207>)
               MAKE_FUNCTION
               STORE_NAME              11 (translate_to_english)

 227           LOAD_CONST             137 (<code object collect_metadata at 0x000001DB02366710, file "wallhaven_gui.py", line 227>)
               MAKE_FUNCTION
               STORE_NAME              12 (collect_metadata)

 338           LOAD_CONST             138 (<code object start at 0x000001DB02367260, file "wallhaven_gui.py", line 338>)
               MAKE_FUNCTION
               STORE_NAME              13 (start)

 412           LOAD_CONST             139 (<code object stop at 0x000001DB021B2A60, file "wallhaven_gui.py", line 412>)
               MAKE_FUNCTION
               STORE_NAME              14 (stop)
               LOAD_CONST             140 (('api_key', 'base_url', 'callback', 'categories', 'downloaded', 'headers', 'image_metadata', 'is_running', 'keyword', 'metadata_ready', 'preview_ready_callback', 'purity', 'save_dir', 'skipped', 'target'))
               STORE_NAME              15 (__static_attributes__)
               LOAD_FAST_BORROW         0 (__classdict__)
               STORE_NAME              16 (__classdictcell__)
               LOAD_CONST             130 (None)
               RETURN_VALUE

Disassembly of <code object __init__ at 0x000001DB020223D0, file "wallhaven_gui.py", line 152>:
152           RESUME                   0

156           LOAD_FAST_BORROW_LOAD_FAST_BORROW 16 (keyword, self)
              STORE_ATTR               0 (keyword)

157           LOAD_FAST_BORROW_LOAD_FAST_BORROW 32 (save_dir, self)
              STORE_ATTR               1 (save_dir)

158           LOAD_FAST_BORROW_LOAD_FAST_BORROW 48 (target, self)
              STORE_ATTR               2 (target)

159           LOAD_FAST_BORROW_LOAD_FAST_BORROW 64 (callback, self)
              STORE_ATTR               3 (callback)

160           LOAD_FAST_BORROW_LOAD_FAST_BORROW 192 (preview_ready_callback, self)
              STORE_ATTR               4 (preview_ready_callback)

161           LOAD_FAST_BORROW_LOAD_FAST_BORROW 176 (api_key, self)
              STORE_ATTR               5 (api_key)

164           LOAD_FAST_BORROW         0 (self)
              LOAD_ATTR               13 (_build_categories_string + NULL|self)
              LOAD_FAST_BORROW_LOAD_FAST_BORROW 86 (category_general, category_anime)
              LOAD_FAST_BORROW         7 (category_people)
              CALL                     3
              LOAD_FAST_BORROW         0 (self)
              STORE_ATTR               7 (categories)

167           LOAD_FAST_BORROW         0 (self)
              LOAD_ATTR               17 (_build_purity_string + NULL|self)
              LOAD_FAST_BORROW_LOAD_FAST_BORROW 137 (purity_sfw, purity_sketchy)
              LOAD_FAST_BORROW        10 (purity_nsfw)
              CALL                     3
              LOAD_FAST_BORROW         0 (self)
              STORE_ATTR               9 (purity)

170           LOAD_CONST               0 ('User-Agent')
              LOAD_CONST               1 ('Mozilla/5.0 (Windows NT 10.0; Win64; x64) AppleWebKit/537.36 (KHTML, like Gecko) Chrome/124.0.0.0 Safari/537.36')

169           BUILD_MAP                1
              LOAD_FAST_BORROW         0 (self)
              STORE_ATTR              10 (headers)

173           LOAD_CONST               2 ('https://wallhaven.cc/api/v1/search')
              LOAD_FAST_BORROW         0 (self)
              STORE_ATTR              11 (base_url)

174           LOAD_SMALL_INT           0
              LOAD_FAST_BORROW         0 (self)
              STORE_ATTR              12 (downloaded)

175           LOAD_SMALL_INT           0
              LOAD_FAST_BORROW         0 (self)
              STORE_ATTR              13 (skipped)

176           LOAD_CONST               3 (False)
              LOAD_FAST_BORROW         0 (self)
              STORE_ATTR              14 (is_running)

179           BUILD_LIST               0
              LOAD_FAST_BORROW         0 (self)
              STORE_ATTR              15 (image_metadata)

180           LOAD_CONST               3 (False)
              LOAD_FAST_BORROW         0 (self)
              STORE_ATTR              16 (metadata_ready)
              LOAD_CONST               4 (None)
              RETURN_VALUE

Disassembly of <code object _build_categories_string at 0x000001DB022149B0, file "wallhaven_gui.py", line 182>:
182           RESUME                   0

188           LOAD_FAST_BORROW         1 (general)
              TO_BOOL
              POP_JUMP_IF_FALSE        3 (to L1)
              NOT_TAKEN
              LOAD_CONST               1 ('1')
              JUMP_FORWARD             1 (to L2)
      L1:     LOAD_CONST               2 ('0')
      L2:     FORMAT_SIMPLE
              LOAD_FAST_BORROW         2 (anime)
              TO_BOOL
              POP_JUMP_IF_FALSE        3 (to L3)
              NOT_TAKEN
              LOAD_CONST               1 ('1')
              JUMP_FORWARD             1 (to L4)
      L3:     LOAD_CONST               2 ('0')
      L4:     FORMAT_SIMPLE
              LOAD_FAST_BORROW         3 (people)
              TO_BOOL
              POP_JUMP_IF_FALSE        5 (to L5)
              NOT_TAKEN
              LOAD_CONST               1 ('1')
              FORMAT_SIMPLE
              BUILD_STRING             3
              RETURN_VALUE
      L5:     LOAD_CONST               2 ('0')
              FORMAT_SIMPLE
              BUILD_STRING             3
              RETURN_VALUE

Disassembly of <code object _build_purity_string at 0x000001DB02214160, file "wallhaven_gui.py", line 190>:
190           RESUME                   0

196           LOAD_FAST_BORROW         1 (sfw)
              TO_BOOL
              POP_JUMP_IF_FALSE        3 (to L1)
              NOT_TAKEN
              LOAD_CONST               1 ('1')
              JUMP_FORWARD             1 (to L2)
      L1:     LOAD_CONST               2 ('0')
      L2:     FORMAT_SIMPLE
              LOAD_FAST_BORROW         2 (sketchy)
              TO_BOOL
              POP_JUMP_IF_FALSE        3 (to L3)
              NOT_TAKEN
              LOAD_CONST               1 ('1')
              JUMP_FORWARD             1 (to L4)
      L3:     LOAD_CONST               2 ('0')
      L4:     FORMAT_SIMPLE
              LOAD_FAST_BORROW         3 (nsfw)
              TO_BOOL
              POP_JUMP_IF_FALSE        5 (to L5)
              NOT_TAKEN
              LOAD_CONST               1 ('1')
              FORMAT_SIMPLE
              BUILD_STRING             3
              RETURN_VALUE
      L5:     LOAD_CONST               2 ('0')
              FORMAT_SIMPLE
              BUILD_STRING             3
              RETURN_VALUE

Disassembly of <code object log at 0x000001DB021B6F70, file "wallhaven_gui.py", line 198>:
198           RESUME                   0

200           LOAD_FAST_BORROW         0 (self)
              LOAD_ATTR                0 (callback)
              TO_BOOL
              POP_JUMP_IF_FALSE       20 (to L1)
              NOT_TAKEN

201           LOAD_FAST_BORROW         0 (self)
              LOAD_ATTR                1 (callback + NULL|self)
              LOAD_FAST_BORROW         1 (message)
              CALL                     1
              POP_TOP
              LOAD_CONST               1 (None)
              RETURN_VALUE

200   L1:     LOAD_CONST               1 (None)
              RETURN_VALUE

Disassembly of <code object contains_chinese at 0x000001DB021B71B0, file "wallhaven_gui.py", line 203>:
203           RESUME                   0

205           LOAD_GLOBAL              1 (bool + NULL)
              LOAD_GLOBAL              2 (re)
              LOAD_ATTR                4 (search)
              PUSH_NULL
              LOAD_CONST               1 ('[\\u4e00-\\u9fff]')
              LOAD_FAST_BORROW         1 (text)
              CALL                     2
              CALL                     1
              RETURN_VALUE

Disassembly of <code object translate_to_english at 0x000001DB02554830, file "wallhaven_gui.py", line 207>:
 207            RESUME                   0

 209            NOP

 211    L1:     LOAD_FAST_BORROW         0 (self)
                LOAD_ATTR                1 (contains_chinese + NULL|self)
                LOAD_FAST_BORROW         1 (text)
                CALL                     1
                TO_BOOL
                POP_JUMP_IF_TRUE         5 (to L5)
        L2:     NOT_TAKEN

 212    L3:     LOAD_FAST_BORROW         1 (text)
                LOAD_CONST               1 (False)
                BUILD_TUPLE              2
        L4:     RETURN_VALUE

 215    L5:     LOAD_FAST_BORROW_LOAD_FAST_BORROW 16 (text, self)
                LOAD_ATTR                2 (PROPER_NOUNS)
                CONTAINS_OP              0 (in)
                POP_JUMP_IF_FALSE       22 (to L7)
                NOT_TAKEN

 216            LOAD_FAST_BORROW         0 (self)
                LOAD_ATTR                2 (PROPER_NOUNS)
                LOAD_FAST_BORROW         1 (text)
                BINARY_OP               26 ([])
                LOAD_CONST               2 (True)
                BUILD_TUPLE              2
        L6:     RETURN_VALUE

 219    L7:     LOAD_GLOBAL              5 (GoogleTranslator + NULL)
                LOAD_CONST               3 ('zh-CN')
                LOAD_CONST               4 ('en')
                LOAD_CONST               5 (('source', 'target'))
                CALL_KW                  2
                STORE_FAST               2 (translator)

 220            LOAD_FAST_BORROW         2 (translator)
                LOAD_ATTR                7 (translate + NULL|self)
                LOAD_FAST_BORROW         1 (text)
                CALL                     1
                STORE_FAST               3 (translated)

 222            LOAD_FAST_BORROW         3 (translated)
                LOAD_CONST               2 (True)
                BUILD_TUPLE              2
        L8:     RETURN_VALUE

  --    L9:     PUSH_EXC_INFO

 223            LOAD_GLOBAL              8 (Exception)
                CHECK_EXC_MATCH
                POP_JUMP_IF_FALSE       36 (to L14)
                NOT_TAKEN
                STORE_FAST               4 (e)

 224   L10:     LOAD_FAST                0 (self)
                LOAD_ATTR               11 (log + NULL|self)
